oct_to_tiff/__init__.py
oct_to_tiff/cli.py
oct_to_tiff-0.6.0.dist-info/licenses/LICENSE.txt
oct_to_tiff-0.6.0.dist-info/METADATA
oct_to_tiff-0.6.0.dist-info/WHEEL
oct_to_tiff-0.6.0.dist-info/entry_points.txt
oct_to_tiff-0.6.0.dist-info/top_level.txt
oct_to_tiff-0.6.0.dist-info/RECORD
