Metadata-Version: 2.4
Name: oct-to-tiff
Version: 0.6.0
Summary: A command line tool for converting optical coherence tomography angiography (OCTA) data.
Author-email: Cameron Lloyd <lloyd@med.unideb.hu>
Maintainer-email: Cameron Lloyd <lloyd@med.unideb.hu>
License-Expression: BSD-3-Clause
Project-URL: Homepage, https://github.com/camlloyd/oct-to-tiff
Project-URL: Bug Tracker, https://github.com/camlloyd/oct-to-tiff/issues
Project-URL: Changelog, https://github.com/camlloyd/oct-to-tiff/blob/main/CHANGELOG.md
Keywords: angiography,cli,oct,octa
Classifier: Development Status :: 3 - Alpha
Classifier: Intended Audience :: Science/Research
Classifier: Natural Language :: English
Classifier: Operating System :: OS Independent
Classifier: Programming Language :: Python :: 3
Classifier: Programming Language :: Python :: 3.11
Classifier: Programming Language :: Python :: 3.12
Classifier: Programming Language :: Python :: 3.13
Classifier: Programming Language :: Python :: 3.14
Requires-Python: >=3.11
License-File: LICENSE.txt
Requires-Dist: defusedxml
Requires-Dist: numpy
Requires-Dist: roifile
Requires-Dist: tifffile
Provides-Extra: dev
Requires-Dist: mypy; extra == "dev"
Requires-Dist: ruff; extra == "dev"
Requires-Dist: types-defusedxml; extra == "dev"
Dynamic: license-file
